{
    "7pusekGNE-o": 1056377,
    "Rk54JNn7Qw4": 2227479,
    "aQ1iXj4oXfI": 1097210,
    "hBfDlIN0WtI": 3734407,
    "gQ7l_hav-bA": 1366734,
    "aLu4oyQ2zdw": 1946726,
    "WNH_ReRMt5k": 1823114,
    "nTxTTZ0QLrI": 3127961,
    "ReuFa_D1Vok": 3339852,
    "Grx5AhU14QU": 2016786,
    "WdUBD5slEnc": 1537785,
    "qP52sh7PzYA": 6158928,
    "iZhbx2mcmug": 2667447,
    "Ktu_LGjGd7A": 1969047,
    "KYvq8-xY1Gg": 2012717,
    "MAP3cnAexxM": 1571763,
    "Rs-Y9MtHsoo": 9400530,
    "tltXZSiAAdQ": 4138234,
    "x9a0_2aGeWU": 2162244,
    "7xx66mR_HeE": 9227227,
    "1SQWKDr_GfA": 1348174,
    "5Z4emyH-fME": 2889797,
    "I8JZbNTl5rM": 2831836,
    "x_BjvhMW9TE": 8554862,
    "rNwzfyr07SM": 2668388,
    "uhbvX4GUrpE": 6530456,
    "YJRFD1AdaUE": 14556160,
    "nV1DHIWSdEo": 8575583,
    "XEKPn3WbksE": 3985452,
    "zKLgrxHDgls": 10721034,
    "F2lWsUJotmc": 2622868,
    "D8piCp9XMKA": 9735795,
    "MKXSWXlSOB0": 2278536,
    "ZBk4V-uqcXs": 3824046,
    "3boaeE3dwMs": 9074780,
    "7GZGTse6dUs": 6426706,
    "FEfJB32wvsk": 5659585,
    "drCopBcrxRM": 11441062,
    "D0W44Z3D3wo": 4737134,
    "_ZCf_iLMwn0": 5576604,
    "fPZ37t3nvco": 13968262,
    "yT5S7Cy5cCE": 5807011,
    "S4gEJIyLHlM": 14315528,
    "fagRTasDcKo": 8459233
}