{
    "7pusekGNE-o": 794260,
    "Rk54JNn7Qw4": 1885301,
    "aQ1iXj4oXfI": 1066058,
    "hBfDlIN0WtI": 3606335,
    "gQ7l_hav-bA": 1299237,
    "aLu4oyQ2zdw": 1880844,
    "WNH_ReRMt5k": 1774633,
    "nTxTTZ0QLrI": 3046978,
    "ReuFa_D1Vok": 3267774,
    "Grx5AhU14QU": 1984012,
    "WdUBD5slEnc": 1516120,
    "qP52sh7PzYA": 6048343,
    "iZhbx2mcmug": 2625606,
    "Ktu_LGjGd7A": 1952689,
    "KYvq8-xY1Gg": 1989637,
    "MAP3cnAexxM": 1562493,
    "Rs-Y9MtHsoo": 9302732,
    "tltXZSiAAdQ": 4092076,
    "x9a0_2aGeWU": 2133927,
    "7xx66mR_HeE": 9136363,
    "1SQWKDr_GfA": 1340927,
    "5Z4emyH-fME": 2868314,
    "I8JZbNTl5rM": 2788079,
    "x_BjvhMW9TE": 8485427,
    "rNwzfyr07SM": 2638711,
    "uhbvX4GUrpE": 6467743,
    "YJRFD1AdaUE": 14431436,
    "nV1DHIWSdEo": 8477658,
    "XEKPn3WbksE": 3940946,
    "zKLgrxHDgls": 10602921,
    "F2lWsUJotmc": 2610755,
    "D8piCp9XMKA": 9677677,
    "MKXSWXlSOB0": 2268249,
    "ZBk4V-uqcXs": 3806394,
    "3boaeE3dwMs": 9017226,
    "7GZGTse6dUs": 6397339,
    "FEfJB32wvsk": 5636640,
    "drCopBcrxRM": 11397073,
    "D0W44Z3D3wo": 4723133,
    "_ZCf_iLMwn0": 5551085,
    "fPZ37t3nvco": 13913516,
    "yT5S7Cy5cCE": 5789983,
    "S4gEJIyLHlM": 14260988,
    "fagRTasDcKo": 8414847
}