{
    "7pusekGNE-o": 976050,
    "Rk54JNn7Qw4": 2119204,
    "aQ1iXj4oXfI": 1086916,
    "hBfDlIN0WtI": 3690853,
    "gQ7l_hav-bA": 1344181,
    "aLu4oyQ2zdw": 1922152,
    "WNH_ReRMt5k": 1806602,
    "nTxTTZ0QLrI": 3100195,
    "ReuFa_D1Vok": 3314228,
    "Grx5AhU14QU": 2005408,
    "WdUBD5slEnc": 1530078,
    "qP52sh7PzYA": 6117229,
    "iZhbx2mcmug": 2652331,
    "Ktu_LGjGd7A": 1963201,
    "KYvq8-xY1Gg": 2005110,
    "MAP3cnAexxM": 1568418,
    "Rs-Y9MtHsoo": 9366070,
    "tltXZSiAAdQ": 4122184,
    "x9a0_2aGeWU": 2151597,
    "7xx66mR_HeE": 9195375,
    "1SQWKDr_GfA": 1345570,
    "5Z4emyH-fME": 2882544,
    "I8JZbNTl5rM": 2817303,
    "x_BjvhMW9TE": 8529900,
    "rNwzfyr07SM": 2658267,
    "uhbvX4GUrpE": 6509359,
    "YJRFD1AdaUE": 14513379,
    "nV1DHIWSdEo": 8540593,
    "XEKPn3WbksE": 3973338,
    "zKLgrxHDgls": 10681510,
    "F2lWsUJotmc": 2618180,
    "D8piCp9XMKA": 9716230,
    "MKXSWXlSOB0": 2274893,
    "ZBk4V-uqcXs": 3817871,
    "3boaeE3dwMs": 9055784,
    "7GZGTse6dUs": 6416315,
    "FEfJB32wvsk": 5651708,
    "drCopBcrxRM": 11425416,
    "D0W44Z3D3wo": 4732211,
    "_ZCf_iLMwn0": 5567883,
    "fPZ37t3nvco": 13949346,
    "yT5S7Cy5cCE": 5801601,
    "S4gEJIyLHlM": 14295785,
    "fagRTasDcKo": 8447814
}