{
    "7pusekGNE-o": 1061373,
    "Rk54JNn7Qw4": 2235094,
    "aQ1iXj4oXfI": 1097898,
    "hBfDlIN0WtI": 3737520,
    "gQ7l_hav-bA": 1368312,
    "aLu4oyQ2zdw": 1948437,
    "WNH_ReRMt5k": 1824251,
    "nTxTTZ0QLrI": 3129969,
    "ReuFa_D1Vok": 3341638,
    "Grx5AhU14QU": 2017529,
    "WdUBD5slEnc": 1538342,
    "qP52sh7PzYA": 6162055,
    "iZhbx2mcmug": 2668608,
    "Ktu_LGjGd7A": 1969536,
    "KYvq8-xY1Gg": 2013304,
    "MAP3cnAexxM": 1572074,
    "Rs-Y9MtHsoo": 9402999,
    "tltXZSiAAdQ": 4139401,
    "x9a0_2aGeWU": 2162852,
    "7xx66mR_HeE": 9229604,
    "1SQWKDr_GfA": 1348373,
    "5Z4emyH-fME": 2890316,
    "I8JZbNTl5rM": 2832829,
    "x_BjvhMW9TE": 8556708,
    "rNwzfyr07SM": 2669035,
    "uhbvX4GUrpE": 6531620,
    "YJRFD1AdaUE": 14559172,
    "nV1DHIWSdEo": 8578291,
    "XEKPn3WbksE": 3986176,
    "zKLgrxHDgls": 10724089,
    "F2lWsUJotmc": 2623231,
    "D8piCp9XMKA": 9737104,
    "MKXSWXlSOB0": 2278783,
    "ZBk4V-uqcXs": 3824492,
    "3boaeE3dwMs": 9076104,
    "7GZGTse6dUs": 6427579,
    "FEfJB32wvsk": 5660156,
    "drCopBcrxRM": 11442248,
    "D0W44Z3D3wo": 4737473,
    "_ZCf_iLMwn0": 5577189,
    "fPZ37t3nvco": 13969587,
    "yT5S7Cy5cCE": 5807374,
    "S4gEJIyLHlM": 14316651,
    "fagRTasDcKo": 8459988
}