{
    "7pusekGNE-o": 631151,
    "Rk54JNn7Qw4": 1642977,
    "aQ1iXj4oXfI": 1046012,
    "hBfDlIN0WtI": 3540757,
    "gQ7l_hav-bA": 1267931,
    "aLu4oyQ2zdw": 1844893,
    "WNH_ReRMt5k": 1748742,
    "nTxTTZ0QLrI": 2999613,
    "ReuFa_D1Vok": 3235490,
    "Grx5AhU14QU": 1965286,
    "WdUBD5slEnc": 1502854,
    "qP52sh7PzYA": 5990067,
    "iZhbx2mcmug": 2602708,
    "Ktu_LGjGd7A": 1944326,
    "KYvq8-xY1Gg": 1978046,
    "MAP3cnAexxM": 1557144,
    "Rs-Y9MtHsoo": 9255100,
    "tltXZSiAAdQ": 4064167,
    "x9a0_2aGeWU": 2118810,
    "7xx66mR_HeE": 9089399,
    "1SQWKDr_GfA": 1336461,
    "5Z4emyH-fME": 2857774,
    "I8JZbNTl5rM": 2774941,
    "x_BjvhMW9TE": 8456341,
    "rNwzfyr07SM": 2626192,
    "uhbvX4GUrpE": 6440281,
    "YJRFD1AdaUE": 14365808,
    "nV1DHIWSdEo": 8434906,
    "XEKPn3WbksE": 3912598,
    "zKLgrxHDgls": 10538706,
    "F2lWsUJotmc": 2604036,
    "D8piCp9XMKA": 9652765,
    "MKXSWXlSOB0": 2262947,
    "ZBk4V-uqcXs": 3797517,
    "3boaeE3dwMs": 8989362,
    "7GZGTse6dUs": 6383127,
    "FEfJB32wvsk": 5625490,
    "drCopBcrxRM": 11377254,
    "D0W44Z3D3wo": 4716208,
    "_ZCf_iLMwn0": 5538823,
    "fPZ37t3nvco": 13887697,
    "yT5S7Cy5cCE": 5782768,
    "S4gEJIyLHlM": 14237237,
    "fagRTasDcKo": 8404837
}