{
    "7pusekGNE-o": 740665,
    "Rk54JNn7Qw4": 1798031,
    "aQ1iXj4oXfI": 1058693,
    "hBfDlIN0WtI": 3582086,
    "gQ7l_hav-bA": 1287807,
    "aLu4oyQ2zdw": 1868282,
    "WNH_ReRMt5k": 1765266,
    "nTxTTZ0QLrI": 3029667,
    "ReuFa_D1Vok": 3254743,
    "Grx5AhU14QU": 1976717,
    "WdUBD5slEnc": 1511318,
    "qP52sh7PzYA": 6026629,
    "iZhbx2mcmug": 2617030,
    "Ktu_LGjGd7A": 1949456,
    "KYvq8-xY1Gg": 1984881,
    "MAP3cnAexxM": 1560360,
    "Rs-Y9MtHsoo": 9284605,
    "tltXZSiAAdQ": 4081615,
    "x9a0_2aGeWU": 2128080,
    "7xx66mR_HeE": 9118265,
    "1SQWKDr_GfA": 1339364,
    "5Z4emyH-fME": 2864032,
    "I8JZbNTl5rM": 2783113,
    "x_BjvhMW9TE": 8473791,
    "rNwzfyr07SM": 2633971,
    "uhbvX4GUrpE": 6456542,
    "YJRFD1AdaUE": 14405138,
    "nV1DHIWSdEo": 8460740,
    "XEKPn3WbksE": 3929073,
    "zKLgrxHDgls": 10577888,
    "F2lWsUJotmc": 2608254,
    "D8piCp9XMKA": 9667971,
    "MKXSWXlSOB0": 2266343,
    "ZBk4V-uqcXs": 3803052,
    "3boaeE3dwMs": 9006686,
    "7GZGTse6dUs": 6391706,
    "FEfJB32wvsk": 5632354,
    "drCopBcrxRM": 11389265,
    "D0W44Z3D3wo": 4720301,
    "_ZCf_iLMwn0": 5546040,
    "fPZ37t3nvco": 13903325,
    "yT5S7Cy5cCE": 5787150,
    "S4gEJIyLHlM": 14251272,
    "fagRTasDcKo": 8410786
}