{
    "7pusekGNE-o": 641580,
    "Rk54JNn7Qw4": 1658134,
    "aQ1iXj4oXfI": 1047192,
    "hBfDlIN0WtI": 3544657,
    "gQ7l_hav-bA": 1269778,
    "aLu4oyQ2zdw": 1846931,
    "WNH_ReRMt5k": 1750238,
    "nTxTTZ0QLrI": 3002558,
    "ReuFa_D1Vok": 3237079,
    "Grx5AhU14QU": 1966316,
    "WdUBD5slEnc": 1503536,
    "qP52sh7PzYA": 5993409,
    "iZhbx2mcmug": 2604005,
    "Ktu_LGjGd7A": 1944822,
    "KYvq8-xY1Gg": 1978607,
    "MAP3cnAexxM": 1557437,
    "Rs-Y9MtHsoo": 9257762,
    "tltXZSiAAdQ": 4065694,
    "x9a0_2aGeWU": 2119683,
    "7xx66mR_HeE": 9091893,
    "1SQWKDr_GfA": 1336753,
    "5Z4emyH-fME": 2858310,
    "I8JZbNTl5rM": 2775729,
    "x_BjvhMW9TE": 8457780,
    "rNwzfyr07SM": 2626869,
    "uhbvX4GUrpE": 6441680,
    "YJRFD1AdaUE": 14368880,
    "nV1DHIWSdEo": 8437131,
    "XEKPn3WbksE": 3914040,
    "zKLgrxHDgls": 10541992,
    "F2lWsUJotmc": 2604352,
    "D8piCp9XMKA": 9654085,
    "MKXSWXlSOB0": 2263195,
    "ZBk4V-uqcXs": 3798003,
    "3boaeE3dwMs": 8990692,
    "7GZGTse6dUs": 6383764,
    "FEfJB32wvsk": 5626046,
    "drCopBcrxRM": 11378301,
    "D0W44Z3D3wo": 4716465,
    "_ZCf_iLMwn0": 5539428,
    "fPZ37t3nvco": 13889013,
    "yT5S7Cy5cCE": 5783113,
    "S4gEJIyLHlM": 14238202,
    "fagRTasDcKo": 8405339
}