{
    "7pusekGNE-o": 1327283,
    "Rk54JNn7Qw4": 2544159,
    "aQ1iXj4oXfI": 1143890,
    "hBfDlIN0WtI": 3903664,
    "gQ7l_hav-bA": 1452831,
    "aLu4oyQ2zdw": 2070586,
    "WNH_ReRMt5k": 1887953,
    "nTxTTZ0QLrI": 3240637,
    "ReuFa_D1Vok": 3431499,
    "Grx5AhU14QU": 2061330,
    "WdUBD5slEnc": 1578705,
    "qP52sh7PzYA": 6324357,
    "iZhbx2mcmug": 2737485,
    "Ktu_LGjGd7A": 2000287,
    "KYvq8-xY1Gg": 2040066,
    "MAP3cnAexxM": 1587885,
    "Rs-Y9MtHsoo": 9529907,
    "tltXZSiAAdQ": 4201758,
    "x9a0_2aGeWU": 2219014,
    "7xx66mR_HeE": 9343783,
    "1SQWKDr_GfA": 1359263,
    "5Z4emyH-fME": 2919508,
    "I8JZbNTl5rM": 2882330,
    "x_BjvhMW9TE": 8689125,
    "rNwzfyr07SM": 2706785,
    "uhbvX4GUrpE": 6600113,
    "YJRFD1AdaUE": 14714993,
    "nV1DHIWSdEo": 8698282,
    "XEKPn3WbksE": 4030277,
    "zKLgrxHDgls": 10852352,
    "F2lWsUJotmc": 2642323,
    "D8piCp9XMKA": 9819067,
    "MKXSWXlSOB0": 2292444,
    "ZBk4V-uqcXs": 3848355,
    "3boaeE3dwMs": 9137596,
    "7GZGTse6dUs": 6467994,
    "FEfJB32wvsk": 5688681,
    "drCopBcrxRM": 11499485,
    "D0W44Z3D3wo": 4754118,
    "_ZCf_iLMwn0": 5605724,
    "fPZ37t3nvco": 14038685,
    "yT5S7Cy5cCE": 5824939,
    "S4gEJIyLHlM": 14377030,
    "fagRTasDcKo": 8493162
}