{
    "7pusekGNE-o": 1367083,
    "Rk54JNn7Qw4": 2584343,
    "aQ1iXj4oXfI": 1151205,
    "hBfDlIN0WtI": 3929100,
    "gQ7l_hav-bA": 1467527,
    "aLu4oyQ2zdw": 2088140,
    "WNH_ReRMt5k": 1899280,
    "nTxTTZ0QLrI": 3260026,
    "ReuFa_D1Vok": 3447037,
    "Grx5AhU14QU": 2068825,
    "WdUBD5slEnc": 1585476,
    "qP52sh7PzYA": 6351234,
    "iZhbx2mcmug": 2748231,
    "Ktu_LGjGd7A": 2006267,
    "KYvq8-xY1Gg": 2044304,
    "MAP3cnAexxM": 1590379,
    "Rs-Y9MtHsoo": 9552197,
    "tltXZSiAAdQ": 4212952,
    "x9a0_2aGeWU": 2224904,
    "7xx66mR_HeE": 9363756,
    "1SQWKDr_GfA": 1361259,
    "5Z4emyH-fME": 2924838,
    "I8JZbNTl5rM": 2892800,
    "x_BjvhMW9TE": 8709394,
    "rNwzfyr07SM": 2713298,
    "uhbvX4GUrpE": 6612266,
    "YJRFD1AdaUE": 14745301,
    "nV1DHIWSdEo": 8721049,
    "XEKPn3WbksE": 4036727,
    "zKLgrxHDgls": 10875670,
    "F2lWsUJotmc": 2645702,
    "D8piCp9XMKA": 9832207,
    "MKXSWXlSOB0": 2295224,
    "ZBk4V-uqcXs": 3852710,
    "3boaeE3dwMs": 9148688,
    "7GZGTse6dUs": 6475317,
    "FEfJB32wvsk": 5694005,
    "drCopBcrxRM": 11511026,
    "D0W44Z3D3wo": 4757382,
    "_ZCf_iLMwn0": 5611720,
    "fPZ37t3nvco": 14050289,
    "yT5S7Cy5cCE": 5828009,
    "S4gEJIyLHlM": 14387564,
    "fagRTasDcKo": 8499043
}