{
    "7pusekGNE-o": 647710,
    "Rk54JNn7Qw4": 1667104,
    "aQ1iXj4oXfI": 1047828,
    "hBfDlIN0WtI": 3546987,
    "gQ7l_hav-bA": 1270808,
    "aLu4oyQ2zdw": 1848208,
    "WNH_ReRMt5k": 1751101,
    "nTxTTZ0QLrI": 3004282,
    "ReuFa_D1Vok": 3238051,
    "Grx5AhU14QU": 1967006,
    "WdUBD5slEnc": 1504016,
    "qP52sh7PzYA": 5995458,
    "iZhbx2mcmug": 2604728,
    "Ktu_LGjGd7A": 1945096,
    "KYvq8-xY1Gg": 1978912,
    "MAP3cnAexxM": 1557608,
    "Rs-Y9MtHsoo": 9259338,
    "tltXZSiAAdQ": 4066578,
    "x9a0_2aGeWU": 2120202,
    "7xx66mR_HeE": 9093366,
    "1SQWKDr_GfA": 1336880,
    "5Z4emyH-fME": 2858619,
    "I8JZbNTl5rM": 2776195,
    "x_BjvhMW9TE": 8458728,
    "rNwzfyr07SM": 2627192,
    "uhbvX4GUrpE": 6442591,
    "YJRFD1AdaUE": 14370687,
    "nV1DHIWSdEo": 8438488,
    "XEKPn3WbksE": 3914661,
    "zKLgrxHDgls": 10543842,
    "F2lWsUJotmc": 2604574,
    "D8piCp9XMKA": 9654916,
    "MKXSWXlSOB0": 2263386,
    "ZBk4V-uqcXs": 3798322,
    "3boaeE3dwMs": 8991499,
    "7GZGTse6dUs": 6384157,
    "FEfJB32wvsk": 5626481,
    "drCopBcrxRM": 11378926,
    "D0W44Z3D3wo": 4716663,
    "_ZCf_iLMwn0": 5539833,
    "fPZ37t3nvco": 13889761,
    "yT5S7Cy5cCE": 5783343,
    "S4gEJIyLHlM": 14239082,
    "fagRTasDcKo": 8405717
}