{
    "7pusekGNE-o": 855410,
    "Rk54JNn7Qw4": 1969096,
    "aQ1iXj4oXfI": 1073865,
    "hBfDlIN0WtI": 3634417,
    "gQ7l_hav-bA": 1314556,
    "aLu4oyQ2zdw": 1894669,
    "WNH_ReRMt5k": 1785794,
    "nTxTTZ0QLrI": 3065432,
    "ReuFa_D1Vok": 3283525,
    "Grx5AhU14QU": 1991217,
    "WdUBD5slEnc": 1521246,
    "qP52sh7PzYA": 6071139,
    "iZhbx2mcmug": 2635100,
    "Ktu_LGjGd7A": 1956473,
    "KYvq8-xY1Gg": 1994575,
    "MAP3cnAexxM": 1564654,
    "Rs-Y9MtHsoo": 9324131,
    "tltXZSiAAdQ": 4102783,
    "x9a0_2aGeWU": 2139903,
    "7xx66mR_HeE": 9157486,
    "1SQWKDr_GfA": 1342558,
    "5Z4emyH-fME": 2873686,
    "I8JZbNTl5rM": 2798411,
    "x_BjvhMW9TE": 8500546,
    "rNwzfyr07SM": 2646000,
    "uhbvX4GUrpE": 6481983,
    "YJRFD1AdaUE": 14460992,
    "nV1DHIWSdEo": 8500180,
    "XEKPn3WbksE": 3952519,
    "zKLgrxHDgls": 10630978,
    "F2lWsUJotmc": 2613424,
    "D8piCp9XMKA": 9691160,
    "MKXSWXlSOB0": 2270849,
    "ZBk4V-uqcXs": 3810384,
    "3boaeE3dwMs": 9030847,
    "7GZGTse6dUs": 6404188,
    "FEfJB32wvsk": 5641946,
    "drCopBcrxRM": 11406566,
    "D0W44Z3D3wo": 4726224,
    "_ZCf_iLMwn0": 5557064,
    "fPZ37t3nvco": 13926433,
    "yT5S7Cy5cCE": 5794537,
    "S4gEJIyLHlM": 14273009,
    "fagRTasDcKo": 8427008
}