{
    "7pusekGNE-o": 690077,
    "Rk54JNn7Qw4": 1726156,
    "aQ1iXj4oXfI": 1052788,
    "hBfDlIN0WtI": 3562404,
    "gQ7l_hav-bA": 1278168,
    "aLu4oyQ2zdw": 1857106,
    "WNH_ReRMt5k": 1757424,
    "nTxTTZ0QLrI": 3015245,
    "ReuFa_D1Vok": 3245356,
    "Grx5AhU14QU": 1971242,
    "WdUBD5slEnc": 1507177,
    "qP52sh7PzYA": 6009291,
    "iZhbx2mcmug": 2609908,
    "Ktu_LGjGd7A": 1947003,
    "KYvq8-xY1Gg": 1981527,
    "MAP3cnAexxM": 1558792,
    "Rs-Y9MtHsoo": 9270261,
    "tltXZSiAAdQ": 4073023,
    "x9a0_2aGeWU": 2123748,
    "7xx66mR_HeE": 9103902,
    "1SQWKDr_GfA": 1338023,
    "5Z4emyH-fME": 2860919,
    "I8JZbNTl5rM": 2779240,
    "x_BjvhMW9TE": 8465178,
    "rNwzfyr07SM": 2630176,
    "uhbvX4GUrpE": 6448554,
    "YJRFD1AdaUE": 14384967,
    "nV1DHIWSdEo": 8448185,
    "XEKPn3WbksE": 3919900,
    "zKLgrxHDgls": 10557671,
    "F2lWsUJotmc": 2606105,
    "D8piCp9XMKA": 9660480,
    "MKXSWXlSOB0": 2264819,
    "ZBk4V-uqcXs": 3800400,
    "3boaeE3dwMs": 8997845,
    "7GZGTse6dUs": 6387449,
    "FEfJB32wvsk": 5629077,
    "drCopBcrxRM": 11383225,
    "D0W44Z3D3wo": 4718225,
    "_ZCf_iLMwn0": 5542545,
    "fPZ37t3nvco": 13895276,
    "yT5S7Cy5cCE": 5784993,
    "S4gEJIyLHlM": 14243748,
    "fagRTasDcKo": 8407844
}