{
    "7pusekGNE-o": 878016,
    "Rk54JNn7Qw4": 1994916,
    "aQ1iXj4oXfI": 1076133,
    "hBfDlIN0WtI": 3644761,
    "gQ7l_hav-bA": 1320059,
    "aLu4oyQ2zdw": 1899293,
    "WNH_ReRMt5k": 1789427,
    "nTxTTZ0QLrI": 3071188,
    "ReuFa_D1Vok": 3288723,
    "Grx5AhU14QU": 1993488,
    "WdUBD5slEnc": 1522758,
    "qP52sh7PzYA": 6078857,
    "iZhbx2mcmug": 2638048,
    "Ktu_LGjGd7A": 1957535,
    "KYvq8-xY1Gg": 1996148,
    "MAP3cnAexxM": 1565264,
    "Rs-Y9MtHsoo": 9331137,
    "tltXZSiAAdQ": 4106104,
    "x9a0_2aGeWU": 2142032,
    "7xx66mR_HeE": 9164126,
    "1SQWKDr_GfA": 1343060,
    "5Z4emyH-fME": 2875132,
    "I8JZbNTl5rM": 2802689,
    "x_BjvhMW9TE": 8505576,
    "rNwzfyr07SM": 2648396,
    "uhbvX4GUrpE": 6487093,
    "YJRFD1AdaUE": 14469764,
    "nV1DHIWSdEo": 8507463,
    "XEKPn3WbksE": 3956703,
    "zKLgrxHDgls": 10640274,
    "F2lWsUJotmc": 2614177,
    "D8piCp9XMKA": 9695838,
    "MKXSWXlSOB0": 2271537,
    "ZBk4V-uqcXs": 3811613,
    "3boaeE3dwMs": 9035494,
    "7GZGTse6dUs": 6406316,
    "FEfJB32wvsk": 5643701,
    "drCopBcrxRM": 11409813,
    "D0W44Z3D3wo": 4727237,
    "_ZCf_iLMwn0": 5558992,
    "fPZ37t3nvco": 13930582,
    "yT5S7Cy5cCE": 5795797,
    "S4gEJIyLHlM": 14276989,
    "fagRTasDcKo": 8432539
}