{
    "7pusekGNE-o": 953995,
    "Rk54JNn7Qw4": 2090853,
    "aQ1iXj4oXfI": 1084339,
    "hBfDlIN0WtI": 3679918,
    "gQ7l_hav-bA": 1338277,
    "aLu4oyQ2zdw": 1916463,
    "WNH_ReRMt5k": 1802492,
    "nTxTTZ0QLrI": 3093092,
    "ReuFa_D1Vok": 3307923,
    "Grx5AhU14QU": 2002707,
    "WdUBD5slEnc": 1528285,
    "qP52sh7PzYA": 6107056,
    "iZhbx2mcmug": 2648747,
    "Ktu_LGjGd7A": 1961715,
    "KYvq8-xY1Gg": 2003053,
    "MAP3cnAexxM": 1567658,
    "Rs-Y9MtHsoo": 9357592,
    "tltXZSiAAdQ": 4118266,
    "x9a0_2aGeWU": 2149008,
    "7xx66mR_HeE": 9187745,
    "1SQWKDr_GfA": 1344907,
    "5Z4emyH-fME": 2880673,
    "I8JZbNTl5rM": 2814126,
    "x_BjvhMW9TE": 8523833,
    "rNwzfyr07SM": 2655861,
    "uhbvX4GUrpE": 6504077,
    "YJRFD1AdaUE": 14502148,
    "nV1DHIWSdEo": 8532634,
    "XEKPn3WbksE": 3969308,
    "zKLgrxHDgls": 10671370,
    "F2lWsUJotmc": 2617158,
    "D8piCp9XMKA": 9711725,
    "MKXSWXlSOB0": 2274086,
    "ZBk4V-uqcXs": 3816294,
    "3boaeE3dwMs": 9050974,
    "7GZGTse6dUs": 6413789,
    "FEfJB32wvsk": 5649824,
    "drCopBcrxRM": 11421362,
    "D0W44Z3D3wo": 4731022,
    "_ZCf_iLMwn0": 5565852,
    "fPZ37t3nvco": 13944629,
    "yT5S7Cy5cCE": 5800162,
    "S4gEJIyLHlM": 14291279,
    "fagRTasDcKo": 8444407
}