{
    "7pusekGNE-o": 670263,
    "Rk54JNn7Qw4": 1700153,
    "aQ1iXj4oXfI": 1050599,
    "hBfDlIN0WtI": 3555364,
    "gQ7l_hav-bA": 1274869,
    "aLu4oyQ2zdw": 1853228,
    "WNH_ReRMt5k": 1754552,
    "nTxTTZ0QLrI": 3010162,
    "ReuFa_D1Vok": 3242021,
    "Grx5AhU14QU": 1969301,
    "WdUBD5slEnc": 1505789,
    "qP52sh7PzYA": 6003441,
    "iZhbx2mcmug": 2607557,
    "Ktu_LGjGd7A": 1946197,
    "KYvq8-xY1Gg": 1980337,
    "MAP3cnAexxM": 1558223,
    "Rs-Y9MtHsoo": 9265250,
    "tltXZSiAAdQ": 4069981,
    "x9a0_2aGeWU": 2122135,
    "7xx66mR_HeE": 9099072,
    "1SQWKDr_GfA": 1337506,
    "5Z4emyH-fME": 2859792,
    "I8JZbNTl5rM": 2777818,
    "x_BjvhMW9TE": 8462165,
    "rNwzfyr07SM": 2628891,
    "uhbvX4GUrpE": 6445842,
    "YJRFD1AdaUE": 14378324,
    "nV1DHIWSdEo": 8443691,
    "XEKPn3WbksE": 3917574,
    "zKLgrxHDgls": 10551316,
    "F2lWsUJotmc": 2605387,
    "D8piCp9XMKA": 9658019,
    "MKXSWXlSOB0": 2264170,
    "ZBk4V-uqcXs": 3799385,
    "3boaeE3dwMs": 8994765,
    "7GZGTse6dUs": 6385939,
    "FEfJB32wvsk": 5627876,
    "drCopBcrxRM": 11381269,
    "D0W44Z3D3wo": 4717459,
    "_ZCf_iLMwn0": 5541209,
    "fPZ37t3nvco": 13892687,
    "yT5S7Cy5cCE": 5784201,
    "S4gEJIyLHlM": 14241621,
    "fagRTasDcKo": 8406910
}