{
    "7pusekGNE-o": 1129336,
    "Rk54JNn7Qw4": 2327955,
    "aQ1iXj4oXfI": 1108965,
    "hBfDlIN0WtI": 3778225,
    "gQ7l_hav-bA": 1388985,
    "aLu4oyQ2zdw": 1975604,
    "WNH_ReRMt5k": 1838241,
    "nTxTTZ0QLrI": 3157104,
    "ReuFa_D1Vok": 3364378,
    "Grx5AhU14QU": 2029042,
    "WdUBD5slEnc": 1549829,
    "qP52sh7PzYA": 6201305,
    "iZhbx2mcmug": 2683242,
    "Ktu_LGjGd7A": 1975985,
    "KYvq8-xY1Gg": 2021241,
    "MAP3cnAexxM": 1576273,
    "Rs-Y9MtHsoo": 9433173,
    "tltXZSiAAdQ": 4155221,
    "x9a0_2aGeWU": 2182193,
    "7xx66mR_HeE": 9257950,
    "1SQWKDr_GfA": 1351091,
    "5Z4emyH-fME": 2897221,
    "I8JZbNTl5rM": 2844071,
    "x_BjvhMW9TE": 8581617,
    "rNwzfyr07SM": 2678271,
    "uhbvX4GUrpE": 6549083,
    "YJRFD1AdaUE": 14596493,
    "nV1DHIWSdEo": 8609235,
    "XEKPn3WbksE": 3997756,
    "zKLgrxHDgls": 10758151,
    "F2lWsUJotmc": 2627837,
    "D8piCp9XMKA": 9755987,
    "MKXSWXlSOB0": 2282270,
    "ZBk4V-uqcXs": 3829996,
    "3boaeE3dwMs": 9092611,
    "7GZGTse6dUs": 6437731,
    "FEfJB32wvsk": 5666958,
    "drCopBcrxRM": 11456011,
    "D0W44Z3D3wo": 4741630,
    "_ZCf_iLMwn0": 5584537,
    "fPZ37t3nvco": 13985833,
    "yT5S7Cy5cCE": 5811690,
    "S4gEJIyLHlM": 14331939,
    "fagRTasDcKo": 8468477
}