{
    "7pusekGNE-o": 738955,
    "Rk54JNn7Qw4": 1795323,
    "aQ1iXj4oXfI": 1058393,
    "hBfDlIN0WtI": 3581368,
    "gQ7l_hav-bA": 1287414,
    "aLu4oyQ2zdw": 1867759,
    "WNH_ReRMt5k": 1764973,
    "nTxTTZ0QLrI": 3029128,
    "ReuFa_D1Vok": 3254413,
    "Grx5AhU14QU": 1976509,
    "WdUBD5slEnc": 1511135,
    "qP52sh7PzYA": 6026023,
    "iZhbx2mcmug": 2616747,
    "Ktu_LGjGd7A": 1949360,
    "KYvq8-xY1Gg": 1984744,
    "MAP3cnAexxM": 1560299,
    "Rs-Y9MtHsoo": 9284183,
    "tltXZSiAAdQ": 4081260,
    "x9a0_2aGeWU": 2127895,
    "7xx66mR_HeE": 9117719,
    "1SQWKDr_GfA": 1339295,
    "5Z4emyH-fME": 2863811,
    "I8JZbNTl5rM": 2782897,
    "x_BjvhMW9TE": 8473411,
    "rNwzfyr07SM": 2633799,
    "uhbvX4GUrpE": 6456194,
    "YJRFD1AdaUE": 14404325,
    "nV1DHIWSdEo": 8460282,
    "XEKPn3WbksE": 3928771,
    "zKLgrxHDgls": 10577097,
    "F2lWsUJotmc": 2608147,
    "D8piCp9XMKA": 9667565,
    "MKXSWXlSOB0": 2266276,
    "ZBk4V-uqcXs": 3802938,
    "3boaeE3dwMs": 9006211,
    "7GZGTse6dUs": 6391505,
    "FEfJB32wvsk": 5632205,
    "drCopBcrxRM": 11389069,
    "D0W44Z3D3wo": 4720234,
    "_ZCf_iLMwn0": 5545874,
    "fPZ37t3nvco": 13903013,
    "yT5S7Cy5cCE": 5787102,
    "S4gEJIyLHlM": 14250976,
    "fagRTasDcKo": 8410657
}