{
    "7pusekGNE-o": 929916,
    "Rk54JNn7Qw4": 2058368,
    "aQ1iXj4oXfI": 1081547,
    "hBfDlIN0WtI": 3667726,
    "gQ7l_hav-bA": 1332580,
    "aLu4oyQ2zdw": 1910107,
    "WNH_ReRMt5k": 1797818,
    "nTxTTZ0QLrI": 3085313,
    "ReuFa_D1Vok": 3301087,
    "Grx5AhU14QU": 1999437,
    "WdUBD5slEnc": 1526268,
    "qP52sh7PzYA": 6096911,
    "iZhbx2mcmug": 2644988,
    "Ktu_LGjGd7A": 1960219,
    "KYvq8-xY1Gg": 2000906,
    "MAP3cnAexxM": 1566758,
    "Rs-Y9MtHsoo": 9348331,
    "tltXZSiAAdQ": 4113732,
    "x9a0_2aGeWU": 2146483,
    "7xx66mR_HeE": 9179339,
    "1SQWKDr_GfA": 1344219,
    "5Z4emyH-fME": 2878509,
    "I8JZbNTl5rM": 2810695,
    "x_BjvhMW9TE": 8517067,
    "rNwzfyr07SM": 2653174,
    "uhbvX4GUrpE": 6498137,
    "YJRFD1AdaUE": 14490318,
    "nV1DHIWSdEo": 8523605,
    "XEKPn3WbksE": 3965515,
    "zKLgrxHDgls": 10659940,
    "F2lWsUJotmc": 2616097,
    "D8piCp9XMKA": 9706452,
    "MKXSWXlSOB0": 2273192,
    "ZBk4V-uqcXs": 3814485,
    "3boaeE3dwMs": 9045454,
    "7GZGTse6dUs": 6411150,
    "FEfJB32wvsk": 5647700,
    "drCopBcrxRM": 11417112,
    "D0W44Z3D3wo": 4729759,
    "_ZCf_iLMwn0": 5563663,
    "fPZ37t3nvco": 13939766,
    "yT5S7Cy5cCE": 5798699,
    "S4gEJIyLHlM": 14286162,
    "fagRTasDcKo": 8440609
}