{
    "7pusekGNE-o": 1106128,
    "Rk54JNn7Qw4": 2298285,
    "aQ1iXj4oXfI": 1104934,
    "hBfDlIN0WtI": 3764524,
    "gQ7l_hav-bA": 1382294,
    "aLu4oyQ2zdw": 1966178,
    "WNH_ReRMt5k": 1833780,
    "nTxTTZ0QLrI": 3148145,
    "ReuFa_D1Vok": 3356958,
    "Grx5AhU14QU": 2025350,
    "WdUBD5slEnc": 1546030,
    "qP52sh7PzYA": 6189300,
    "iZhbx2mcmug": 2678394,
    "Ktu_LGjGd7A": 1973952,
    "KYvq8-xY1Gg": 2018534,
    "MAP3cnAexxM": 1575041,
    "Rs-Y9MtHsoo": 9423689,
    "tltXZSiAAdQ": 4149964,
    "x9a0_2aGeWU": 2175771,
    "7xx66mR_HeE": 9249174,
    "1SQWKDr_GfA": 1350274,
    "5Z4emyH-fME": 2895136,
    "I8JZbNTl5rM": 2840594,
    "x_BjvhMW9TE": 8572250,
    "rNwzfyr07SM": 2675385,
    "uhbvX4GUrpE": 6543892,
    "YJRFD1AdaUE": 14584803,
    "nV1DHIWSdEo": 8599888,
    "XEKPn3WbksE": 3993411,
    "zKLgrxHDgls": 10748027,
    "F2lWsUJotmc": 2626238,
    "D8piCp9XMKA": 9749771,
    "MKXSWXlSOB0": 2281123,
    "ZBk4V-uqcXs": 3828226,
    "3boaeE3dwMs": 9087486,
    "7GZGTse6dUs": 6434800,
    "FEfJB32wvsk": 5664890,
    "drCopBcrxRM": 11451985,
    "D0W44Z3D3wo": 4740265,
    "_ZCf_iLMwn0": 5582286,
    "fPZ37t3nvco": 13980942,
    "yT5S7Cy5cCE": 5810448,
    "S4gEJIyLHlM": 14327623,
    "fagRTasDcKo": 8465870
}