{
    "7pusekGNE-o": 908109,
    "Rk54JNn7Qw4": 2030518,
    "aQ1iXj4oXfI": 1079057,
    "hBfDlIN0WtI": 3657447,
    "gQ7l_hav-bA": 1327355,
    "aLu4oyQ2zdw": 1904935,
    "WNH_ReRMt5k": 1794322,
    "nTxTTZ0QLrI": 3078756,
    "ReuFa_D1Vok": 3295169,
    "Grx5AhU14QU": 1996720,
    "WdUBD5slEnc": 1524729,
    "qP52sh7PzYA": 6088809,
    "iZhbx2mcmug": 2641848,
    "Ktu_LGjGd7A": 1959085,
    "KYvq8-xY1Gg": 1998481,
    "MAP3cnAexxM": 1566068,
    "Rs-Y9MtHsoo": 9340505,
    "tltXZSiAAdQ": 4110221,
    "x9a0_2aGeWU": 2144448,
    "7xx66mR_HeE": 9172308,
    "1SQWKDr_GfA": 1343668,
    "5Z4emyH-fME": 2877022,
    "I8JZbNTl5rM": 2807497,
    "x_BjvhMW9TE": 8511846,
    "rNwzfyr07SM": 2651105,
    "uhbvX4GUrpE": 6493164,
    "YJRFD1AdaUE": 14480840,
    "nV1DHIWSdEo": 8516292,
    "XEKPn3WbksE": 3961185,
    "zKLgrxHDgls": 10651106,
    "F2lWsUJotmc": 2615159,
    "D8piCp9XMKA": 9701758,
    "MKXSWXlSOB0": 2272441,
    "ZBk4V-uqcXs": 3813157,
    "3boaeE3dwMs": 9040996,
    "7GZGTse6dUs": 6408924,
    "FEfJB32wvsk": 5645842,
    "drCopBcrxRM": 11413645,
    "D0W44Z3D3wo": 4728499,
    "_ZCf_iLMwn0": 5561533,
    "fPZ37t3nvco": 13935613,
    "yT5S7Cy5cCE": 5797415,
    "S4gEJIyLHlM": 14281990,
    "fagRTasDcKo": 8437120
}