{
    "7pusekGNE-o": 1388814,
    "Rk54JNn7Qw4": 2607737,
    "aQ1iXj4oXfI": 1155713,
    "hBfDlIN0WtI": 3944235,
    "gQ7l_hav-bA": 1475977,
    "aLu4oyQ2zdw": 2098345,
    "WNH_ReRMt5k": 1905515,
    "nTxTTZ0QLrI": 3270955,
    "ReuFa_D1Vok": 3456146,
    "Grx5AhU14QU": 2073128,
    "WdUBD5slEnc": 1589446,
    "qP52sh7PzYA": 6366783,
    "iZhbx2mcmug": 2754774,
    "Ktu_LGjGd7A": 2009483,
    "KYvq8-xY1Gg": 2047264,
    "MAP3cnAexxM": 1592200,
    "Rs-Y9MtHsoo": 9566040,
    "tltXZSiAAdQ": 4221413,
    "x9a0_2aGeWU": 2228399,
    "7xx66mR_HeE": 9376164,
    "1SQWKDr_GfA": 1362786,
    "5Z4emyH-fME": 2928348,
    "I8JZbNTl5rM": 2900165,
    "x_BjvhMW9TE": 8721292,
    "rNwzfyr07SM": 2717587,
    "uhbvX4GUrpE": 6619717,
    "YJRFD1AdaUE": 14764514,
    "nV1DHIWSdEo": 8735264,
    "XEKPn3WbksE": 4040451,
    "zKLgrxHDgls": 10890072,
    "F2lWsUJotmc": 2648089,
    "D8piCp9XMKA": 9840332,
    "MKXSWXlSOB0": 2297166,
    "ZBk4V-uqcXs": 3855904,
    "3boaeE3dwMs": 9156137,
    "7GZGTse6dUs": 6480477,
    "FEfJB32wvsk": 5697471,
    "drCopBcrxRM": 11517705,
    "D0W44Z3D3wo": 4759873,
    "_ZCf_iLMwn0": 5615737,
    "fPZ37t3nvco": 14057455,
    "yT5S7Cy5cCE": 5830544,
    "S4gEJIyLHlM": 14394806,
    "fagRTasDcKo": 8502883
}