{
    "7pusekGNE-o": 1420361,
    "Rk54JNn7Qw4": 2646001,
    "aQ1iXj4oXfI": 1161638,
    "hBfDlIN0WtI": 3967943,
    "gQ7l_hav-bA": 1488653,
    "aLu4oyQ2zdw": 2113558,
    "WNH_ReRMt5k": 1914341,
    "nTxTTZ0QLrI": 3288279,
    "ReuFa_D1Vok": 3469028,
    "Grx5AhU14QU": 2079038,
    "WdUBD5slEnc": 1594601,
    "qP52sh7PzYA": 6390997,
    "iZhbx2mcmug": 2764560,
    "Ktu_LGjGd7A": 2013805,
    "KYvq8-xY1Gg": 2050432,
    "MAP3cnAexxM": 1595171,
    "Rs-Y9MtHsoo": 9587477,
    "tltXZSiAAdQ": 4233164,
    "x9a0_2aGeWU": 2232520,
    "7xx66mR_HeE": 9395255,
    "1SQWKDr_GfA": 1364934,
    "5Z4emyH-fME": 2932956,
    "I8JZbNTl5rM": 2910120,
    "x_BjvhMW9TE": 8738806,
    "rNwzfyr07SM": 2723247,
    "uhbvX4GUrpE": 6630440,
    "YJRFD1AdaUE": 14790655,
    "nV1DHIWSdEo": 8757499,
    "XEKPn3WbksE": 4046101,
    "zKLgrxHDgls": 10912510,
    "F2lWsUJotmc": 2651479,
    "D8piCp9XMKA": 9852180,
    "MKXSWXlSOB0": 2299522,
    "ZBk4V-uqcXs": 3859941,
    "3boaeE3dwMs": 9167793,
    "7GZGTse6dUs": 6487071,
    "FEfJB32wvsk": 5702063,
    "drCopBcrxRM": 11527730,
    "D0W44Z3D3wo": 4763295,
    "_ZCf_iLMwn0": 5621600,
    "fPZ37t3nvco": 14068940,
    "yT5S7Cy5cCE": 5833727,
    "S4gEJIyLHlM": 14405590,
    "fagRTasDcKo": 8508013
}